Workbook

Sheet Cover & Notes
A1: Thread & Salt -- 5-Year Financial History
A2: Prepared for internal planning use -- revenue, units and summary P&L, FY2021 through July 2026 YTD.
A4: Currency | B4: GBP (£), unrounded to the nearest pound
A5: Period covered | B5: FY2021 (partial, founding year) through July 2026 (year to date)
A6: Monthly detail available from | B6: January 2024 onward -- see "Methodology" below for FY2021-2023
A8: Methodology
A9: FY2021-2023 figures | B9: Annual totals only. The business ran on a handwritten/spreadsheet order log until migrating to the current order-tracking system in January 2024; no reliable monthly split survives from before that migration.
A10: Cost of goods sold (COGS) | B10: Modelled at a flat 42% of revenue across all periods, based on the company's own product costing (consistent unit economics across the product range).
A11: Operating expense categories | B11: Marketing & advertising and Fulfilment & shipping are modelled as a percentage of revenue (variable costs); Founders' compensation and Software & other overhead are modelled as fixed monthly amounts (see "Assumptions" tab) that step up periodically rather than scaling with revenue -- this is why a revenue dip compresses net margin by more than the revenue drop alone.
A12: Rate/rounding note | B12: All modelled rates and fixed costs are shown on the Assumptions tab; formulas throughout this workbook reference those cells directly, so changing an assumption recalculates every downstream figure.
A14: Legend
A15: Blue text | B15: Hardcoded input (a real or assumed figure)
A16: Black text | B16: Formula (calculated from other cells)
A17: Green text | B17: Link to a value on another sheet
A18: Yellow fill | B18: Key assumption -- see Assumptions tab

Sheet Annual Financial Summary
A1: Annual Financial Summary
B3: FY2021* | C3: FY2022* | D3: FY2023* | E3: FY2024 | F3: FY2025 | G3: FY2026 (YTD Jul)
A4: Revenue | B4: 215600 | C4: 467400 | D4: 532800 | E4: =SUM('Monthly Revenue History'!B2:B13) -> 588800 | F4: =SUM('Monthly Revenue History'!B14:B25) -> 638802 | G4: =SUM('Monthly Revenue History'!B26:B32) -> 347342
A5: Cost of goods sold | B5: =B4*Assumptions!$B$4 -> 90552 | C5: =C4*Assumptions!$B$4 -> 196308 | D5: =D4*Assumptions!$B$4 -> 223776 | E5: =E4*Assumptions!$B$4 -> 247296 | F5: =F4*Assumptions!$B$4 -> 268296.84 | G5: =G4*Assumptions!$B$4 -> 145883.64
A6: Gross profit | B6: =B4-B5 -> 125048 | C6: =C4-C5 -> 271092 | D6: =D4-D5 -> 309024 | E6: =E4-E5 -> 341504 | F6: =F4-F5 -> 370505.16 | G6: =G4-G5 -> 201458.36
A7: Gross margin % | B7: =B6/B4 -> 0.58 | C7: =C6/C4 -> 0.58 | D7: =D6/D4 -> 0.58 | E7: =E6/E4 -> 0.58 | F7: =F6/F4 -> 0.58 | G7: =G6/G4 -> 0.58
A9: Marketing & advertising | B9: =B4*Assumptions!$B$5 -> 30184 | C9: =C4*Assumptions!$B$5 -> 65436 | D9: =D4*Assumptions!$B$5 -> 74592 | E9: =E4*Assumptions!$B$5 -> 82432 | F9: =F4*Assumptions!$B$5 -> 89432.28 | G9: =G4*Assumptions!$B$5 -> 48627.88
A10: Fulfilment & shipping | B10: =B4*Assumptions!$B$6 -> 19404 | C10: =C4*Assumptions!$B$6 -> 42066 | D10: =D4*Assumptions!$B$6 -> 47952 | E10: =E4*Assumptions!$B$6 -> 52992 | F10: =F4*Assumptions!$B$6 -> 57492.18 | G10: =G4*Assumptions!$B$6 -> 31260.78
A11: Platform & payment fees | B11: =B4*Assumptions!$B$7 -> 7546 | C11: =C4*Assumptions!$B$7 -> 16359 | D11: =D4*Assumptions!$B$7 -> 18648 | E11: =E4*Assumptions!$B$7 -> 20608 | F11: =F4*Assumptions!$B$7 -> 22358.07 | G11: =G4*Assumptions!$B$7 -> 12156.97
A12: Founders' compensation | B12: =Assumptions!$B$11*12 -> 38400 | C12: =Assumptions!$B$11*12 -> 38400 | D12: =Assumptions!$B$11*12 -> 38400 | E12: =Assumptions!$B$11*12 -> 38400 | F12: =Assumptions!$C$11*12 -> 42000 | G12: =Assumptions!$D$11*7 -> 25900
A13: Software, subscriptions & other | B13: =Assumptions!$B$12*12 -> 10200 | C13: =Assumptions!$B$12*12 -> 10200 | D13: =Assumptions!$B$12*12 -> 10200 | E13: =Assumptions!$B$12*12 -> 10200 | F13: =Assumptions!$C$12*12 -> 11400 | G13: =Assumptions!$D$12*7 -> 6650
A14: Total operating expenses | B14: =SUM(B9:B13) -> 105734 | C14: =SUM(C9:C13) -> 172461 | D14: =SUM(D9:D13) -> 189792 | E14: =SUM(E9:E13) -> 204632 | F14: =SUM(F9:F13) -> 222682.53 | G14: =SUM(G9:G13) -> 124595.63
A16: Net profit | B16: =B6-B14 -> 19314 | C16: =C6-C14 -> 98631 | D16: =D6-D14 -> 119232 | E16: =E6-E14 -> 136872 | F16: =F6-F14 -> 147822.63 | G16: =G6-G14 -> 76862.73
A17: Net margin % | B17: =B16/B4 -> 0.08958256 | C17: =C16/C4 -> 0.21102054 | D17: =D16/D4 -> 0.22378378 | E17: =E16/E4 -> 0.23245924 | F17: =F16/F4 -> 0.23140602 | G17: =G16/G4 -> 0.22128833
A19: * FY2021-2023: annual-only figures (see Cover & Notes -- "Methodology"). Fixed operating costs for these years are modelled using the 2024 monthly rate, the earliest rate on record.

Sheet Monthly Revenue History
A1: Month | B1: Revenue (£) | C1: Units | D1: Rev / unit (£) | E1: MoM growth | F1: YoY growth
A2: 2024-01 | B2: 51517 | C2: 813 | D2: =B2/C2 -> 63.366544
A3: 2024-02 | B3: 45199 | C3: 681 | D3: =B3/C3 -> 66.371512 | E3: =(B3-B2)/B2 -> -0.12263913
A4: 2024-03 | B4: 39715 | C4: 600 | D4: =B4/C4 -> 66.191667 | E4: =(B4-B3)/B3 -> -0.12133012
A5: 2024-04 | B5: 38620 | C5: 619 | D5: =B5/C5 -> 62.390953 | E5: =(B5-B4)/B4 -> -0.027571447
A6: 2024-05 | B6: 49438 | C6: 745 | D6: =B6/C6 -> 66.359732 | E6: =(B6-B5)/B5 -> 0.28011393
A7: 2024-06 | B7: 47473 | C7: 755 | D7: =B7/C7 -> 62.878146 | E7: =(B7-B6)/B6 -> -0.039746754
A8: 2024-07 | B8: 51523 | C8: 828 | D8: =B8/C8 -> 62.225845 | E8: =(B8-B7)/B7 -> 0.085311651
A9: 2024-08 | B9: 49218 | C9: 776 | D9: =B9/C9 -> 63.425258 | E9: =(B9-B8)/B8 -> -0.044737302
A10: 2024-09 | B10: 44027 | C10: 669 | D10: =B10/C10 -> 65.810164 | E10: =(B10-B9)/B9 -> -0.10546954
A11: 2024-10 | B11: 51095 | C11: 784 | D11: =B11/C11 -> 65.172194 | E11: =(B11-B10)/B10 -> 0.16053785
A12: 2024-11 | B12: 57698 | C12: 905 | D12: =B12/C12 -> 63.754696 | E12: =(B12-B11)/B11 -> 0.12922987
A13: 2024-12 | B13: 63277 | C13: 976 | D13: =B13/C13 -> 64.832992 | E13: =(B13-B12)/B12 -> 0.096693126
A14: 2025-01 | B14: 55464 | C14: 846 | D14: =B14/C14 -> 65.560284 | E14: =(B14-B13)/B13 -> -0.12347298 | F14: =(B14-B2)/B2 -> 0.076615486
A15: 2025-02 | B15: 49530 | C15: 768 | D15: =B15/C15 -> 64.492188 | E15: =(B15-B14)/B14 -> -0.10698832 | F15: =(B15-B3)/B3 -> 0.095820704
A16: 2025-03 | B16: 43524 | C16: 697 | D16: =B16/C16 -> 62.444763 | E16: =(B16-B15)/B15 -> -0.12125984 | F16: =(B16-B4)/B4 -> 0.095908347
A17: 2025-04 | B17: 44188 | C17: 693 | D17: =B17/C17 -> 63.763348 | E17: =(B17-B16)/B16 -> 0.015255951 | F17: =(B17-B5)/B5 -> 0.144174
A18: 2025-05 | B18: 50554 | C18: 805 | D18: =B18/C18 -> 62.8 | E18: =(B18-B17)/B17 -> 0.14406626 | F18: =(B18-B6)/B6 -> 0.022573729
A19: 2025-06 | B19: 54134 | C19: 862 | D19: =B19/C19 -> 62.800464 | E19: =(B19-B18)/B18 -> 0.070815366 | F19: =(B19-B7)/B7 -> 0.14031133
A20: 2025-07 | B20: 53644 | C20: 841 | D20: =B20/C20 -> 63.785969 | E20: =(B20-B19)/B19 -> -0.0090516127 | F20: =(B20-B8)/B8 -> 0.041166081
A21: 2025-08 | B21: 52796 | C21: 837 | D21: =B21/C21 -> 63.077658 | E21: =(B21-B20)/B20 -> -0.015807919 | F21: =(B21-B9)/B9 -> 0.072696981
A22: 2025-09 | B22: 48188 | C22: 761 | D22: =B22/C22 -> 63.321945 | E22: =(B22-B21)/B21 -> -0.087279339 | F22: =(B22-B10)/B10 -> 0.094510187
A23: 2025-10 | B23: 52980 | C23: 824 | D23: =B23/C23 -> 64.296117 | E23: =(B23-B22)/B22 -> 0.099443845 | F23: =(B23-B11)/B11 -> 0.036892064
A24: 2025-11 | B24: 65336 | C24: 996 | D24: =B24/C24 -> 65.598394 | E24: =(B24-B23)/B23 -> 0.23322008 | F24: =(B24-B12)/B12 -> 0.13237894
A25: 2025-12 | B25: 68464 | C25: 1029 | D25: =B25/C25 -> 66.5345 | E25: =(B25-B24)/B24 -> 0.047875597 | F25: =(B25-B13)/B13 -> 0.081972913
... A32: 2026-07 | B32: 41850 | C32: 638 | D32: =B32/C32 -> 65.595611 | E32: =(B32-B31)/B31 -> -0.24412094 | F32: =(B32-B20)/B20 -> -0.21985683
A34: Monthly detail begins January 2024 (see Cover & Notes -- "Methodology"). January 2025-June 2026 figures reconcile exactly to the committed order-line data (data/hackathon-1/threadandsalt-sales-data.csv).

Sheet Assumptions
A1: Key assumptions
A3: Rate-based assumptions
A4: Cost of goods sold, % of revenue | B4: 0.42
A5: Marketing & advertising, % of revenue | B5: 0.14
A6: Fulfilment & shipping, % of revenue | B6: 0.09
A7: Platform & payment processing fees, % of revenue | B7: 0.035
A9: Fixed monthly costs (annualised as x12 on the Annual sheet)
A10: Cost line | B10: 2024 | C10: 2025 | D10: 2026
A11: Founders' compensation / drawings (£/month) | B11: 3200 | C11: 3500 | D11: 3700
A12: Software, subscriptions & other overhead (£/month) | B12: 850 | C12: 950 | D12: 950
A14: FY2021-2023 fixed costs (below) are modelled using the 2024 monthly rate x12, since no separate figure survives for those earlier years -- the same limitation noted on the Cover tab.
